lavender_dir_tree/__init__.py
Lavender_Dir_Tree-1.0.2.dist-info/LICENSE
Lavender_Dir_Tree-1.0.2.dist-info/METADATA
Lavender_Dir_Tree-1.0.2.dist-info/WHEEL
Lavender_Dir_Tree-1.0.2.dist-info/top_level.txt
Lavender_Dir_Tree-1.0.2.dist-info/RECORD
