Metadata-Version: 2.1
Name: Lavender-Dir-Tree
Version: 1.0.2
Summary: A pip package for listing files.
Home-page: https://github.com/Zeyu-Xie/Lavender-Dir-Tree
Author: Zeyu Xie
Author-email: xie.zeyu20@gmail.com
Classifier: Programming Language :: Python :: 3
Classifier: License :: OSI Approved :: GNU General Public License v3 (GPLv3)
Classifier: Operating System :: OS Independent
Requires-Python: >=3.6
License-File: LICENSE
